[
  {
    "source": "i am in home page",
    "steps": [
      {
        "name": "i am in home page",
        "aggregatedDurations": {
          "median": 7.3648166,
          "average": 7.3648166
        },
        "durations": [
          {
            "duration": 7.3648166,
            "location": "file:///C:/Users/lenis/IdeaProjects/BDDWebAutomationFramework_WA_NY_Team2/Aetna/src/test/java/features/HomePage.feature:4"
          }
        ]
      }
    ]
  },
  {
    "source": "I click shop for a plan",
    "steps": [
      {
        "name": "I click shop for a plan",
        "aggregatedDurations": {
          "median": 0.1089869,
          "average": 0.1089869
        },
        "durations": [
          {
            "duration": 0.1089869,
            "location": "file:///C:/Users/lenis/IdeaProjects/BDDWebAutomationFramework_WA_NY_Team2/Aetna/src/test/java/features/HomePage.feature:29"
          }
        ]
      }
    ]
  },
  {
    "source": "I go Health coverage",
    "steps": [
      {
        "name": "I go Health coverage",
        "aggregatedDurations": {
          "median": 0.1219996,
          "average": 0.1219996
        },
        "durations": [
          {
            "duration": 0.1219996,
            "location": "file:///C:/Users/lenis/IdeaProjects/BDDWebAutomationFramework_WA_NY_Team2/Aetna/src/test/java/features/HomePage.feature:30"
          }
        ]
      }
    ]
  },
  {
    "source": "I click find a doctor",
    "steps": [
      {
        "name": "I click find a doctor",
        "aggregatedDurations": {
          "median": 0.8565167,
          "average": 0.8565167
        },
        "durations": [
          {
            "duration": 0.8565167,
            "location": "file:///C:/Users/lenis/IdeaProjects/BDDWebAutomationFramework_WA_NY_Team2/Aetna/src/test/java/features/HomePage.feature:31"
          }
        ]
      }
    ]
  }
]