[
  {
    "line": 1,
    "elements": [
      {
        "start_timestamp": "2020-09-13T04:44:17.810Z",
        "line": 4,
        "name": "TD Bank Online Banking page is displayed",
        "description": "",
        "id": "td-bank-home-page-functionality-test;td-bank-online-banking-page-is-displayed",
        "after": [
          {
            "result": {
              "duration": 858200400,
              "status": "passed"
            },
            "match": {
              "location": "stepdefinitions.TDHomePageStepDefinitions.closeBrowser()"
            }
          }
        ],
        "type": "scenario",
        "keyword": "Scenario",
        "steps": [
          {
            "result": {
              "duration": 8232672400,
              "status": "passed"
            },
            "before": [
              {
                "result": {
                  "duration": 35003800,
                  "status": "passed"
                },
                "match": {
                  "location": "stepdefinitions.TDHomePageStepDefinitions.getInIt()"
                }
              }
            ],
            "line": 5,
            "name": "I am on TD bank home page.",
            "match": {
              "location": "stepdefinitions.TDHomePageStepDefinitions.i_am_on_td_bank_home_page()"
            },
            "keyword": "Given "
          },
          {
            "result": {
              "duration": 190014500,
              "status": "passed"
            },
            "before": [
              {
                "result": {
                  "duration": 1003600,
                  "status": "passed"
                },
                "match": {
                  "location": "stepdefinitions.TDHomePageStepDefinitions.getInIt()"
                }
              }
            ],
            "line": 6,
            "name": "i mouse hover on LogIn",
            "match": {
              "location": "stepdefinitions.TDHomePageStepDefinitions.i_mouse_hover_on_log_in()"
            },
            "keyword": "When "
          },
          {
            "result": {
              "duration": 15481256300,
              "status": "passed"
            },
            "before": [
              {
                "result": {
                  "duration": 1003100,
                  "status": "passed"
                },
                "match": {
                  "location": "stepdefinitions.TDHomePageStepDefinitions.getInIt()"
                }
              }
            ],
            "line": 7,
            "name": "i click on Online Banking",
            "match": {
              "location": "stepdefinitions.TDHomePageStepDefinitions.i_click_on_online_banking()"
            },
            "keyword": "And "
          }
        ],
        "tags": [
          {
            "name": "@SmokeTest"
          }
        ]
      }
    ],
    "name": "TD Bank Home page functionality test",
    "description": "",
    "id": "td-bank-home-page-functionality-test",
    "keyword": "Feature",
    "uri": "file:src/test/java/features/TDBankHomePage.feature",
    "tags": []
  }
]