[
  {
    "line": 1,
    "elements": [
      {
        "line": 3,
        "name": "",
        "description": "",
        "type": "background",
        "keyword": "Background",
        "steps": [
          {
            "result": {
              "duration": 10126095300,
              "status": "passed"
            },
            "before": [
              {
                "result": {
                  "duration": 26927700,
                  "status": "passed"
                },
                "match": {
                  "location": "stepdefinitions.UnitedAirHomeStepDefinition.getInit()"
                }
              }
            ],
            "line": 4,
            "name": "I am in home page",
            "match": {
              "location": "stepdefinitions.UnitedAirHomeStepDefinition.i_am_in_home_page()"
            },
            "keyword": "Given "
          }
        ]
      },
      {
        "start_timestamp": "2020-09-18T06:46:18.347Z",
        "line": 15,
        "name": "United Airlines Book Hotels test",
        "description": "",
        "id": "united-airlines-home-page-functionality-test;united-airlines-book-hotels-test",
        "after": [
          {
            "result": {
              "duration": 759215700,
              "status": "passed"
            },
            "match": {
              "location": "stepdefinitions.UnitedAirHomeStepDefinition.tearDown(io.cucumber.java.Scenario)"
            }
          }
        ],
        "type": "scenario",
        "keyword": "Scenario",
        "steps": [
          {
            "result": {
              "duration": 190490600,
              "status": "passed"
            },
            "before": [
              {
                "result": {
                  "duration": 2990200,
                  "status": "passed"
                },
                "match": {
                  "location": "stepdefinitions.UnitedAirHomeStepDefinition.getInit()"
                }
              }
            ],
            "line": 16,
            "name": "I click on book button",
            "match": {
              "location": "stepdefinitions.UnitedAirHomeStepDefinition.i_click_on_book_button()"
            },
            "keyword": "When "
          },
          {
            "result": {
              "duration": 256380200,
              "status": "passed"
            },
            "before": [
              {
                "result": {
                  "duration": 999200,
                  "status": "passed"
                },
                "match": {
                  "location": "stepdefinitions.UnitedAirHomeStepDefinition.getInit()"
                }
              }
            ],
            "line": 17,
            "name": "I click on Hotels button",
            "match": {
              "location": "stepdefinitions.UnitedAirHomeStepDefinition.i_click_on_hotels_button()"
            },
            "keyword": "And "
          },
          {
            "result": {
              "duration": 4357219600,
              "status": "passed"
            },
            "before": [
              {
                "result": {
                  "duration": 1986800,
                  "status": "passed"
                },
                "match": {
                  "location": "stepdefinitions.UnitedAirHomeStepDefinition.getInit()"
                }
              }
            ],
            "line": 18,
            "name": "I enter \"Las Vegas\" in where to searchBox and submit",
            "match": {
              "arguments": [
                {
                  "val": "\"Las Vegas\"",
                  "offset": 8
                }
              ],
              "location": "stepdefinitions.UnitedAirHomeStepDefinition.i_enter_in_where_to_search_box_and_submit(java.lang.String)"
            },
            "keyword": "And "
          },
          {
            "result": {
              "duration": 44877200,
              "status": "passed"
            },
            "before": [
              {
                "result": {
                  "duration": 988000,
                  "status": "passed"
                },
                "match": {
                  "location": "stepdefinitions.UnitedAirHomeStepDefinition.getInit()"
                }
              }
            ],
            "line": 19,
            "name": "I validate Las Vegas landed page properly",
            "match": {
              "location": "stepdefinitions.UnitedAirHomeStepDefinition.i_validate_las_vegas_landed_page_properly()"
            },
            "keyword": "Then "
          }
        ],
        "tags": [
          {
            "name": "@SmokeTest"
          }
        ]
      }
    ],
    "name": "United Airlines home page functionality test",
    "description": "",
    "id": "united-airlines-home-page-functionality-test",
    "keyword": "Feature",
    "uri": "file:src/test/java/features/UnitedAirlinesHome.feature",
    "tags": []
  }
]